{
  "data": {
    "site": {
      "siteMetadata": {
        "title": "Intelligible Babble",
        "author": "Leland Richardson"
      }
    },
    "markdownRemark": null
  },
  "pageContext": {
    "slug": "/generation-rss-feed-actions-in-aspnet-mvc/",
    "previous": {
      "fields": { "slug": "/how-to-write-maintainable-jquery-applications/" },
      "frontmatter": {
        "title": "How to write Maintainable jQuery Applications"
      }
    },
    "next": {
      "fields": {
        "slug": "/building-an-image-uploading--resizing-framework-in-aspnet/"
      },
      "frontmatter": {
        "title": "Building an Image Uploading & Resizing Framework in ASP.Net"
      }
    }
  }
}
